parseq/__init__.py
parseq/callclaude.py
parseq/disambiguate.py
parseq/parseq.py
parseq/parseq.q
parseq/parseq_ns.q
parseq/q_operators.md
gabiteodoru_parseq-0.1.3.dist-info/METADATA
gabiteodoru_parseq-0.1.3.dist-info/WHEEL
gabiteodoru_parseq-0.1.3.dist-info/top_level.txt
gabiteodoru_parseq-0.1.3.dist-info/RECORD
