Metadata-Version: 2.4
Name: gabiteodoru-parseq
Version: 0.1.3
Summary: ParseQ: Q Language to Python Translator with AI-Powered Disambiguation
Home-page: https://github.com/gabiteodoru/parseq
Author: Gabi Teodoru
Author-email: gabiteodoru@gmail.com
Keywords: q kdb parseq compiler translator ai claude functional-programming
Classifier: Development Status :: 4 - Beta
Classifier: Intended Audience :: Developers
Classifier: License :: OSI Approved :: MIT License
Classifier: Operating System :: OS Independent
Classifier: Programming Language :: Python :: 3
Classifier: Programming Language :: Python :: 3.8
Classifier: Programming Language :: Python :: 3.9
Classifier: Programming Language :: Python :: 3.10
Classifier: Programming Language :: Python :: 3.11
Classifier: Programming Language :: Python :: 3.12
Classifier: Topic :: Software Development :: Compilers
Classifier: Topic :: Software Development :: Code Generators
Classifier: Topic :: Scientific/Engineering
Requires-Python: >=3.8
Dynamic: author
Dynamic: author-email
Dynamic: classifier
Dynamic: description
Dynamic: description-content-type
Dynamic: home-page
Dynamic: keywords
Dynamic: requires-python
Dynamic: summary
